{
  "task_id": "train_002",
  "case_id": "CASE-HEAD-207",
  "patient_id": "PAT-2207",
  "primary_assessment": "mild_traumatic_brain_injury_without_loss_of_consciousness",
  "risk_tier": "intermediate",
  "disposition": "home_observation_with_followup",
  "imaging_recommendation": "no_immediate_ct",
  "red_flags": [
    "head_impact",
    "mild_nausea",
    "coordination_symptom_observe"
  ],
  "absent_red_flags": [
    "loss_of_consciousness",
    "repeated_vomiting",
    "seizure",
    "focal_weakness"
  ],
  "restrictions": [
    "no_driving_until_symptom_free",
    "no_high_risk_sports_until_cleared",
    "relative_cognitive_physical_rest",
    "return_to_learn_accommodations"
  ],
  "follow_up": {
    "timeframe_hours": 48,
    "route": "primary_care_or_concussion_recheck"
  },
  "evidence_ids": [
    "CASE-HEAD-207",
    "OBS-HEAD-207-GCS",
    "OBS-HEAD-207-NEURO"
  ],
  "safety_checks": {
    "no_false_loc": true,
    "no_false_vomiting": true,
    "no_false_photophobia": true
  }
}
