[
  {
    "account_aliases": [
      "Globex North",
      "Globex North Holdings",
      "GlobexNorth Ops",
      "Globex North Subsidiary"
    ],
    "account_id": "acct_globex_north",
    "billing_arr_current": 1188000.0,
    "contract_tenure_months": 29,
    "crm_arr": 1057320.0,
    "csm_owner": "Maya Chen",
    "display_name": "Globex North",
    "legal_name": "Globex North Holdings LLC",
    "lifecycle_status": "active",
    "product_plan": "Scale",
    "region": "North America",
    "renewal_date": "2026-09-11",
    "segment": "Enterprise"
  },
  {
    "account_aliases": [
      "Northstar Finance",
      "Northstar Finance Group",
      "NorthstarFinance Ops",
      "Northstar Finance Subsidiary"
    ],
    "account_id": "acct_northstar_finance",
    "billing_arr_current": 1425000.0,
    "contract_tenure_months": 12,
    "crm_arr": 1268250.0,
    "csm_owner": "Owen Patel",
    "display_name": "Northstar Finance",
    "legal_name": "Northstar Finance Group Inc.",
    "lifecycle_status": "active",
    "product_plan": "Strategic",
    "region": "North America",
    "renewal_date": "2026-08-27",
    "segment": "Strategic"
  },
  {
    "account_aliases": [
      "Northstar Retail",
      "Northstar Retail Services",
      "NorthstarRetail Ops"
    ],
    "account_id": "acct_northstar_retail",
    "billing_arr_current": 234000.0,
    "contract_tenure_months": 13,
    "crm_arr": 234000.0,
    "csm_owner": "Riley Brooks",
    "display_name": "Northstar Retail",
    "legal_name": "Northstar Retail Services LLC",
    "lifecycle_status": "active",
    "product_plan": "Scale",
    "region": "North America",
    "renewal_date": "2026-02-15",
    "segment": "Mid-Market"
  },
  {
    "account_aliases": [
      "Polaris Health",
      "Polaris Health Network",
      "PolarisHealth Ops"
    ],
    "account_id": "acct_polaris_health",
    "billing_arr_current": 708000.0,
    "contract_tenure_months": 76,
    "crm_arr": 708000.0,
    "csm_owner": "Ari Morgan",
    "display_name": "Polaris Health",
    "legal_name": "Polaris Health Network Inc.",
    "lifecycle_status": "active",
    "product_plan": "Enterprise",
    "region": "North America",
    "renewal_date": "2026-08-10",
    "segment": "Enterprise"
  },
  {
    "account_aliases": [
      "Meridian Energy",
      "Meridian Energy Partners",
      "MeridianEnergy Ops"
    ],
    "account_id": "acct_meridian_energy",
    "billing_arr_current": 444000.0,
    "contract_tenure_months": 54,
    "crm_arr": 444000.0,
    "csm_owner": "Samira Khan",
    "display_name": "Meridian Energy",
    "legal_name": "Meridian Energy Partners LLC",
    "lifecycle_status": "active",
    "product_plan": "Scale",
    "region": "EMEA",
    "renewal_date": "2026-02-05",
    "segment": "Enterprise"
  },
  {
    "account_aliases": [
      "Cobalt Media",
      "Cobalt Media Works",
      "CobaltMedia Ops"
    ],
    "account_id": "acct_cobalt_media",
    "billing_arr_current": 330000.0,
    "contract_tenure_months": 60,
    "crm_arr": 330000.0,
    "csm_owner": "Jordan Lee",
    "display_name": "Cobalt Media",
    "legal_name": "Cobalt Media Works Inc.",
    "lifecycle_status": "implementation",
    "product_plan": "Scale",
    "region": "North America",
    "renewal_date": "2026-11-17",
    "segment": "Mid-Market"
  },
  {
    "account_aliases": [
      "Zenith Labs",
      "Zenith Labs",
      "ZenithLabs Ops"
    ],
    "account_id": "acct_zenith_labs",
    "billing_arr_current": 612000.0,
    "contract_tenure_months": 21,
    "crm_arr": 612000.0,
    "csm_owner": "Elena Ruiz",
    "display_name": "Zenith Labs",
    "legal_name": "Zenith Labs GmbH",
    "lifecycle_status": "active",
    "product_plan": "Enterprise",
    "region": "EMEA",
    "renewal_date": "2026-05-21",
    "segment": "Enterprise"
  },
  {
    "account_aliases": [
      "Lumen Rail",
      "Lumen Rail Systems",
      "LumenRail Ops"
    ],
    "account_id": "acct_lumen_rail",
    "billing_arr_current": 1150000.0,
    "contract_tenure_months": 72,
    "crm_arr": 966000.0,
    "csm_owner": "Noah Becker",
    "display_name": "Lumen Rail",
    "legal_name": "Lumen Rail Systems Ltd.",
    "lifecycle_status": "active",
    "product_plan": "Enterprise",
    "region": "EMEA",
    "renewal_date": "2026-03-09",
    "segment": "Strategic"
  },
  {
    "account_aliases": [
      "Orbitax",
      "Orbitax Solutions Pty",
      "Orbitax Ops"
    ],
    "account_id": "acct_orbitax",
    "billing_arr_current": 300000.0,
    "contract_tenure_months": 34,
    "crm_arr": 300000.0,
    "csm_owner": "Maya Chen",
    "display_name": "Orbitax",
    "legal_name": "Orbitax Solutions Pty Ltd.",
    "lifecycle_status": "renewal_risk",
    "product_plan": "Scale",
    "region": "APAC",
    "renewal_date": "2026-11-09",
    "segment": "Mid-Market"
  },
  {
    "account_aliases": [
      "Arcstone",
      "Arcstone Manufacturing",
      "Arcstone Ops"
    ],
    "account_id": "acct_arcstone",
    "billing_arr_current": 540000.0,
    "contract_tenure_months": 71,
    "crm_arr": 540000.0,
    "csm_owner": "Owen Patel",
    "display_name": "Arcstone",
    "legal_name": "Arcstone Manufacturing Inc.",
    "lifecycle_status": "renewal_risk",
    "product_plan": "Scale",
    "region": "North America",
    "renewal_date": "2026-06-11",
    "segment": "Enterprise"
  },
  {
    "account_aliases": [
      "BluePeak Outdoors",
      "Bluepeak Outdoors",
      "BluePeakOutdoors Ops"
    ],
    "account_id": "acct_bluepeak",
    "billing_arr_current": 99000.0,
    "contract_tenure_months": 48,
    "crm_arr": 99000.0,
    "csm_owner": "Riley Brooks",
    "display_name": "BluePeak Outdoors",
    "legal_name": "BluePeak Outdoors LLC",
    "lifecycle_status": "active",
    "product_plan": "Growth",
    "region": "North America",
    "renewal_date": "2026-06-22",
    "segment": "SMB"
  },
  {
    "account_aliases": [
      "Summit Grid",
      "Summit Grid Cooperative",
      "SummitGrid Ops"
    ],
    "account_id": "acct_summit_grid",
    "billing_arr_current": 138000.0,
    "contract_tenure_months": 46,
    "crm_arr": 138000.0,
    "csm_owner": "Ari Morgan",
    "display_name": "Summit Grid",
    "legal_name": "Summit Grid Cooperative",
    "lifecycle_status": "active",
    "product_plan": "Scale",
    "region": "North America",
    "renewal_date": "2026-11-26",
    "segment": "Mid-Market"
  },
  {
    "account_aliases": [
      "HarborByte",
      "Harborbyte Systems",
      "HarborByte Ops"
    ],
    "account_id": "acct_harborbyte",
    "billing_arr_current": 57000.0,
    "contract_tenure_months": 86,
    "crm_arr": 57000.0,
    "csm_owner": "Samira Khan",
    "display_name": "HarborByte",
    "legal_name": "HarborByte Systems Inc.",
    "lifecycle_status": "active",
    "product_plan": "Launch",
    "region": "North America",
    "renewal_date": "2026-02-09",
    "segment": "SMB"
  },
  {
    "account_aliases": [
      "Kiteworks Digital",
      "Kiteworks Digital",
      "KiteworksDigital Ops"
    ],
    "account_id": "acct_kiteworks",
    "billing_arr_current": 288000.0,
    "contract_tenure_months": 32,
    "crm_arr": 288000.0,
    "csm_owner": "Jordan Lee",
    "display_name": "Kiteworks Digital",
    "legal_name": "Kiteworks Digital Ltd.",
    "lifecycle_status": "implementation",
    "product_plan": "Scale",
    "region": "EMEA",
    "renewal_date": "2026-11-16",
    "segment": "Mid-Market"
  },
  {
    "account_aliases": [
      "Saffron Hotel",
      "Saffron Hotel Group Pte",
      "SaffronHotel Ops"
    ],
    "account_id": "acct_saffron_hotel",
    "billing_arr_current": 660000.0,
    "contract_tenure_months": 35,
    "crm_arr": 660000.0,
    "csm_owner": "Elena Ruiz",
    "display_name": "Saffron Hotel",
    "legal_name": "Saffron Hotel Group Pte. Ltd.",
    "lifecycle_status": "active",
    "product_plan": "Enterprise",
    "region": "APAC",
    "renewal_date": "2026-05-08",
    "segment": "Enterprise"
  },
  {
    "account_aliases": [
      "Terra Nova Foods",
      "Terra Nova Foods",
      "TerraNovaFoods Ops"
    ],
    "account_id": "acct_terra_nova",
    "billing_arr_current": 156000.0,
    "contract_tenure_months": 51,
    "crm_arr": 156000.0,
    "csm_owner": "Noah Becker",
    "display_name": "Terra Nova Foods",
    "legal_name": "Terra Nova Foods SA",
    "lifecycle_status": "active",
    "product_plan": "Scale",
    "region": "LATAM",
    "renewal_date": "2026-04-25",
    "segment": "Mid-Market"
  },
  {
    "account_aliases": [
      "Riverbend Bank",
      "Riverbend Bank",
      "RiverbendBank Ops"
    ],
    "account_id": "acct_riverbend_bank",
    "billing_arr_current": 900000.0,
    "contract_tenure_months": 55,
    "crm_arr": 900000.0,
    "csm_owner": "Maya Chen",
    "display_name": "Riverbend Bank",
    "legal_name": "Riverbend Bank Corp.",
    "lifecycle_status": "active",
    "product_plan": "Scale",
    "region": "North America",
    "renewal_date": "2026-12-13",
    "segment": "Enterprise"
  },
  {
    "account_aliases": [
      "MetroByte",
      "Metrobyte Telecom",
      "MetroByte Ops"
    ],
    "account_id": "acct_metrobyte",
    "billing_arr_current": 852000.0,
    "contract_tenure_months": 70,
    "crm_arr": 852000.0,
    "csm_owner": "Owen Patel",
    "display_name": "MetroByte",
    "legal_name": "MetroByte Telecom LLC",
    "lifecycle_status": "paused",
    "product_plan": "Enterprise",
    "region": "North America",
    "renewal_date": "2026-08-25",
    "segment": "Enterprise"
  },
  {
    "account_aliases": [
      "Quartz Insurance",
      "Quartz Insurance",
      "QuartzInsurance Ops",
      "Quartz Insurance Subsidiary"
    ],
    "account_id": "acct_quartz_insure",
    "billing_arr_current": 1050000.0,
    "contract_tenure_months": 66,
    "crm_arr": 976500.0,
    "csm_owner": "Riley Brooks",
    "display_name": "Quartz Insurance",
    "legal_name": "Quartz Insurance PLC",
    "lifecycle_status": "renewal_risk",
    "product_plan": "Enterprise",
    "region": "EMEA",
    "renewal_date": "2026-04-26",
    "segment": "Strategic"
  },
  {
    "account_aliases": [
      "Apexia Robotics",
      "Apexia Robotics",
      "ApexiaRobotics Ops"
    ],
    "account_id": "acct_apexia",
    "billing_arr_current": 504000.0,
    "contract_tenure_months": 56,
    "crm_arr": 504000.0,
    "csm_owner": "Ari Morgan",
    "display_name": "Apexia Robotics",
    "legal_name": "Apexia Robotics KK",
    "lifecycle_status": "active",
    "product_plan": "Enterprise",
    "region": "APAC",
    "renewal_date": "2026-03-08",
    "segment": "Enterprise"
  },
  {
    "account_aliases": [
      "Redwood Schools",
      "Redwood School District",
      "RedwoodSchools Ops"
    ],
    "account_id": "acct_redwood_school",
    "billing_arr_current": 111000.0,
    "contract_tenure_months": 33,
    "crm_arr": 111000.0,
    "csm_owner": "Samira Khan",
    "display_name": "Redwood Schools",
    "legal_name": "Redwood School District",
    "lifecycle_status": "active",
    "product_plan": "Launch",
    "region": "North America",
    "renewal_date": "2026-08-25",
    "segment": "SMB"
  },
  {
    "account_aliases": [
      "Eastwind Logistics",
      "Eastwind Logistics",
      "EastwindLogistics Ops"
    ],
    "account_id": "acct_eastwind",
    "billing_arr_current": 174000.0,
    "contract_tenure_months": 40,
    "crm_arr": 174000.0,
    "csm_owner": "Jordan Lee",
    "display_name": "Eastwind Logistics",
    "legal_name": "Eastwind Logistics BV",
    "lifecycle_status": "active",
    "product_plan": "Scale",
    "region": "EMEA",
    "renewal_date": "2026-05-06",
    "segment": "Mid-Market"
  },
  {
    "account_aliases": [
      "Mint Leaf",
      "Mint Leaf Markets",
      "MintLeaf Ops"
    ],
    "account_id": "acct_mint_leaf",
    "billing_arr_current": 96000.0,
    "contract_tenure_months": 55,
    "crm_arr": 96000.0,
    "csm_owner": "Elena Ruiz",
    "display_name": "Mint Leaf",
    "legal_name": "Mint Leaf Markets Inc.",
    "lifecycle_status": "active",
    "product_plan": "Growth",
    "region": "North America",
    "renewal_date": "2026-04-09",
    "segment": "SMB"
  },
  {
    "account_aliases": [
      "Stellar Auto",
      "Stellar Auto Components",
      "StellarAuto Ops"
    ],
    "account_id": "acct_stellar_auto",
    "billing_arr_current": 852000.0,
    "contract_tenure_months": 31,
    "crm_arr": 852000.0,
    "csm_owner": "Noah Becker",
    "display_name": "Stellar Auto",
    "legal_name": "Stellar Auto Components GmbH",
    "lifecycle_status": "active",
    "product_plan": "Scale",
    "region": "EMEA",
    "renewal_date": "2026-08-19",
    "segment": "Enterprise"
  },
  {
    "account_aliases": [
      "Canyon State Health",
      "Canyon State Health",
      "CanyonStateHealth Ops"
    ],
    "account_id": "acct_canyon_state",
    "billing_arr_current": 162000.0,
    "contract_tenure_months": 79,
    "crm_arr": 162000.0,
    "csm_owner": "Maya Chen",
    "display_name": "Canyon State Health",
    "legal_name": "Canyon State Health LLC",
    "lifecycle_status": "renewal_risk",
    "product_plan": "Growth",
    "region": "North America",
    "renewal_date": "2026-04-06",
    "segment": "Mid-Market"
  },
  {
    "account_aliases": [
      "Silverline CU",
      "Silverline Credit Union",
      "SilverlineCU Ops"
    ],
    "account_id": "acct_silverline",
    "billing_arr_current": 63000.0,
    "contract_tenure_months": 79,
    "crm_arr": 63000.0,
    "csm_owner": "Owen Patel",
    "display_name": "Silverline CU",
    "legal_name": "Silverline Credit Union",
    "lifecycle_status": "renewal_risk",
    "product_plan": "Growth",
    "region": "North America",
    "renewal_date": "2026-07-05",
    "segment": "SMB"
  },
  {
    "account_aliases": [
      "Aurora Textiles",
      "Aurora Textiles",
      "AuroraTextiles Ops"
    ],
    "account_id": "acct_aurora_textiles",
    "billing_arr_current": 192000.0,
    "contract_tenure_months": 69,
    "crm_arr": 192000.0,
    "csm_owner": "Riley Brooks",
    "display_name": "Aurora Textiles",
    "legal_name": "Aurora Textiles Ltd.",
    "lifecycle_status": "active",
    "product_plan": "Scale",
    "region": "APAC",
    "renewal_date": "2026-10-05",
    "segment": "Mid-Market"
  },
  {
    "account_aliases": [
      "Bayside Biotech",
      "Bayside Biotech",
      "BaysideBiotech Ops"
    ],
    "account_id": "acct_bayside_bio",
    "billing_arr_current": 552000.0,
    "contract_tenure_months": 20,
    "crm_arr": 513360.0,
    "csm_owner": "Ari Morgan",
    "display_name": "Bayside Biotech",
    "legal_name": "Bayside Biotech Inc.",
    "lifecycle_status": "active",
    "product_plan": "Scale",
    "region": "North America",
    "renewal_date": "2026-12-09",
    "segment": "Enterprise"
  },
  {
    "account_aliases": [
      "Greenfield Agritech",
      "Greenfield Agritech",
      "GreenfieldAgritech Ops"
    ],
    "account_id": "acct_greenfield",
    "billing_arr_current": 264000.0,
    "contract_tenure_months": 13,
    "crm_arr": 264000.0,
    "csm_owner": "Samira Khan",
    "display_name": "Greenfield Agritech",
    "legal_name": "Greenfield Agritech SA",
    "lifecycle_status": "active",
    "product_plan": "Growth",
    "region": "LATAM",
    "renewal_date": "2026-07-20",
    "segment": "Mid-Market"
  },
  {
    "account_aliases": [
      "CloudNine Travel",
      "Cloudnine Travel Group",
      "CloudNineTravel Ops"
    ],
    "account_id": "acct_cloudnine",
    "billing_arr_current": 162000.0,
    "contract_tenure_months": 54,
    "crm_arr": 162000.0,
    "csm_owner": "Jordan Lee",
    "display_name": "CloudNine Travel",
    "legal_name": "CloudNine Travel Group Inc.",
    "lifecycle_status": "active",
    "product_plan": "Growth",
    "region": "North America",
    "renewal_date": "2026-02-12",
    "segment": "Mid-Market"
  },
  {
    "account_aliases": [
      "Valence Payments",
      "Valence Payment Services",
      "ValencePayments Ops",
      "Valence Payments Subsidiary"
    ],
    "account_id": "acct_valence",
    "billing_arr_current": 540000.0,
    "contract_tenure_months": 31,
    "crm_arr": 599400.0,
    "csm_owner": "Elena Ruiz",
    "display_name": "Valence Payments",
    "legal_name": "Valence Payment Services LLC",
    "lifecycle_status": "paused",
    "product_plan": "Scale",
    "region": "North America",
    "renewal_date": "2026-12-07",
    "segment": "Enterprise"
  },
  {
    "account_aliases": [
      "Peakstone Capital",
      "Peakstone Capital",
      "PeakstoneCapital Ops"
    ],
    "account_id": "acct_peakstone",
    "billing_arr_current": 1300000.0,
    "contract_tenure_months": 69,
    "crm_arr": 1300000.0,
    "csm_owner": "Noah Becker",
    "display_name": "Peakstone Capital",
    "legal_name": "Peakstone Capital Ltd.",
    "lifecycle_status": "renewal_risk",
    "product_plan": "Enterprise",
    "region": "EMEA",
    "renewal_date": "2026-09-13",
    "segment": "Strategic"
  },
  {
    "account_aliases": [
      "BrightHarbor",
      "Brightharbor Clinics",
      "BrightHarbor Ops"
    ],
    "account_id": "acct_brightharbor",
    "billing_arr_current": 672000.0,
    "contract_tenure_months": 64,
    "crm_arr": 672000.0,
    "csm_owner": "Maya Chen",
    "display_name": "BrightHarbor",
    "legal_name": "BrightHarbor Clinics Inc.",
    "lifecycle_status": "active",
    "product_plan": "Scale",
    "region": "North America",
    "renewal_date": "2026-03-06",
    "segment": "Enterprise"
  },
  {
    "account_aliases": [
      "TandemWorks",
      "Tandemworks Software",
      "TandemWorks Ops"
    ],
    "account_id": "acct_tandemworks",
    "billing_arr_current": 90000.0,
    "contract_tenure_months": 7,
    "crm_arr": 90000.0,
    "csm_owner": "Owen Patel",
    "display_name": "TandemWorks",
    "legal_name": "TandemWorks Software Oy",
    "lifecycle_status": "active",
    "product_plan": "Launch",
    "region": "EMEA",
    "renewal_date": "2026-05-21",
    "segment": "SMB"
  },
  {
    "account_aliases": [
      "Nimbus Fleet",
      "Nimbus Fleet Services Pty",
      "NimbusFleet Ops"
    ],
    "account_id": "acct_nimbus_fleet",
    "billing_arr_current": 174000.0,
    "contract_tenure_months": 10,
    "crm_arr": 174000.0,
    "csm_owner": "Riley Brooks",
    "display_name": "Nimbus Fleet",
    "legal_name": "Nimbus Fleet Services Pty Ltd.",
    "lifecycle_status": "active",
    "product_plan": "Growth",
    "region": "APAC",
    "renewal_date": "2026-06-21",
    "segment": "Mid-Market"
  },
  {
    "account_aliases": [
      "Solstice Renewables",
      "Solstice Renewables",
      "SolsticeRenewables Ops"
    ],
    "account_id": "acct_solstice",
    "billing_arr_current": 864000.0,
    "contract_tenure_months": 65,
    "crm_arr": 768960.0,
    "csm_owner": "Ari Morgan",
    "display_name": "Solstice Renewables",
    "legal_name": "Solstice Renewables Inc.",
    "lifecycle_status": "active",
    "product_plan": "Enterprise",
    "region": "North America",
    "renewal_date": "2026-08-21",
    "segment": "Enterprise"
  },
  {
    "account_aliases": [
      "OpalCare",
      "Opalcare Pharmacy Group",
      "OpalCare Ops"
    ],
    "account_id": "acct_opalcare",
    "billing_arr_current": 240000.0,
    "contract_tenure_months": 70,
    "crm_arr": 240000.0,
    "csm_owner": "Samira Khan",
    "display_name": "OpalCare",
    "legal_name": "OpalCare Pharmacy Group",
    "lifecycle_status": "active",
    "product_plan": "Growth",
    "region": "APAC",
    "renewal_date": "2026-03-15",
    "segment": "Mid-Market"
  },
  {
    "account_aliases": [
      "Everline Apparel",
      "Everline Apparel",
      "EverlineApparel Ops"
    ],
    "account_id": "acct_everline",
    "billing_arr_current": 96000.0,
    "contract_tenure_months": 10,
    "crm_arr": 96000.0,
    "csm_owner": "Jordan Lee",
    "display_name": "Everline Apparel",
    "legal_name": "Everline Apparel LLC",
    "lifecycle_status": "active",
    "product_plan": "Launch",
    "region": "North America",
    "renewal_date": "2026-09-21",
    "segment": "SMB"
  },
  {
    "account_aliases": [
      "Westport Port",
      "Westport Port Authority",
      "WestportPort Ops"
    ],
    "account_id": "acct_westport",
    "billing_arr_current": 564000.0,
    "contract_tenure_months": 55,
    "crm_arr": 564000.0,
    "csm_owner": "Elena Ruiz",
    "display_name": "Westport Port",
    "legal_name": "Westport Port Authority",
    "lifecycle_status": "active",
    "product_plan": "Scale",
    "region": "North America",
    "renewal_date": "2026-01-07",
    "segment": "Enterprise"
  },
  {
    "account_aliases": [
      "Helios Devices",
      "Helios Medical Devices",
      "HeliosDevices Ops"
    ],
    "account_id": "acct_helios",
    "billing_arr_current": 408000.0,
    "contract_tenure_months": 22,
    "crm_arr": 408000.0,
    "csm_owner": "Noah Becker",
    "display_name": "Helios Devices",
    "legal_name": "Helios Medical Devices AG",
    "lifecycle_status": "active",
    "product_plan": "Scale",
    "region": "EMEA",
    "renewal_date": "2026-08-18",
    "segment": "Enterprise"
  },
  {
    "account_aliases": [
      "Foxtrot Foodservice",
      "Foxtrot Foodservice",
      "FoxtrotFoodservice Ops"
    ],
    "account_id": "acct_foxtrot",
    "billing_arr_current": 246000.0,
    "contract_tenure_months": 76,
    "crm_arr": 246000.0,
    "csm_owner": "Maya Chen",
    "display_name": "Foxtrot Foodservice",
    "legal_name": "Foxtrot Foodservice Inc.",
    "lifecycle_status": "active",
    "product_plan": "Growth",
    "region": "North America",
    "renewal_date": "2026-01-23",
    "segment": "Mid-Market"
  },
  {
    "account_aliases": [
      "Southridge Mining",
      "Southridge Mining",
      "SouthridgeMining Ops"
    ],
    "account_id": "acct_southridge",
    "billing_arr_current": 588000.0,
    "contract_tenure_months": 60,
    "crm_arr": 523320.0,
    "csm_owner": "Owen Patel",
    "display_name": "Southridge Mining",
    "legal_name": "Southridge Mining Ltd.",
    "lifecycle_status": "active",
    "product_plan": "Scale",
    "region": "LATAM",
    "renewal_date": "2026-01-21",
    "segment": "Enterprise"
  },
  {
    "account_aliases": [
      "Lakeshore Media",
      "Lakeshore Public Media",
      "LakeshoreMedia Ops"
    ],
    "account_id": "acct_lakeshore",
    "billing_arr_current": 60000.0,
    "contract_tenure_months": 48,
    "crm_arr": 60000.0,
    "csm_owner": "Riley Brooks",
    "display_name": "Lakeshore Media",
    "legal_name": "Lakeshore Public Media",
    "lifecycle_status": "active",
    "product_plan": "Launch",
    "region": "North America",
    "renewal_date": "2026-01-11",
    "segment": "SMB"
  },
  {
    "account_aliases": [
      "Vectorline Security",
      "Vectorline Security Systems",
      "VectorlineSecurity Ops"
    ],
    "account_id": "acct_vectorline",
    "billing_arr_current": 198000.0,
    "contract_tenure_months": 66,
    "crm_arr": 198000.0,
    "csm_owner": "Ari Morgan",
    "display_name": "Vectorline Security",
    "legal_name": "Vectorline Security Systems LLC",
    "lifecycle_status": "active",
    "product_plan": "Growth",
    "region": "North America",
    "renewal_date": "2026-03-17",
    "segment": "Mid-Market"
  }
]
