{
  "deal_id": "D-ORBIT-384",
  "policy_id": "P-CARVEOUT-OPS-2026",
  "priority_issues": [
    {
      "issue_id": "CLOSING_DEADLINE",
      "clause_code": "CLOSE",
      "severity": "HIGH",
      "recommended_action": "EXTEND_AND_ESCALATE",
      "approval_owner": "OPERATIONS_COMMITTEE",
      "source_doc_ids": [
        "DOC-ORBIT384-DRAFT-02",
        "DOC-ORBIT384-EMAIL-03",
        "DOC-ORBIT384-MATCON-05"
      ]
    },
    {
      "issue_id": "EMPLOYEE_TRANSFER",
      "clause_code": "EMPLOYEE",
      "severity": "HIGH",
      "recommended_action": "REVISE_AND_ESCALATE",
      "approval_owner": "HR_COMMITTEE",
      "source_doc_ids": [
        "DOC-ORBIT384-DISC-06",
        "DOC-ORBIT384-DRAFT-02",
        "DOC-ORBIT384-EMAIL-03"
      ]
    },
    {
      "issue_id": "ESCROW_PERCENT",
      "clause_code": "ESCROW",
      "severity": "MEDIUM",
      "recommended_action": "REDUCE_OR_ESCALATE",
      "approval_owner": "DEAL_LEAD",
      "source_doc_ids": [
        "DOC-ORBIT384-DRAFT-02",
        "DOC-ORBIT384-FIN-04"
      ]
    },
    {
      "issue_id": "IP_TRANSITION",
      "clause_code": "IP",
      "severity": "HIGH",
      "recommended_action": "NARROW_AND_ESCALATE",
      "approval_owner": "IP_COUNSEL",
      "source_doc_ids": [
        "DOC-ORBIT384-DISC-06",
        "DOC-ORBIT384-DRAFT-02",
        "DOC-ORBIT384-EMAIL-03"
      ]
    },
    {
      "issue_id": "RESTRICTIVE_COVENANT",
      "clause_code": "NONCOMPETE",
      "severity": "HIGH",
      "recommended_action": "NARROW_AND_ESCALATE",
      "approval_owner": "EMPLOYMENT_COUNSEL",
      "source_doc_ids": [
        "DOC-ORBIT384-DRAFT-02",
        "DOC-ORBIT384-EMAIL-03"
      ]
    },
    {
      "issue_id": "TSA_SERVICE_CONTINUITY",
      "clause_code": "TSA",
      "severity": "HIGH",
      "recommended_action": "REVISE_AND_ESCALATE",
      "approval_owner": "OPERATIONS_COMMITTEE",
      "source_doc_ids": [
        "DOC-ORBIT384-DISC-06",
        "DOC-ORBIT384-DRAFT-02",
        "DOC-ORBIT384-EMAIL-03",
        "DOC-ORBIT384-MATCON-05"
      ]
    }
  ],
  "transition_flags": {
    "employee_transfer": {
      "issue_present": true,
      "draft_offer_percent": 70.0,
      "seller_warn_or_severance_retained": true,
      "required_offer_standard": "BUYER_COMPARABLE_OFFERS_ALL_BUSINESS_EMPLOYEES",
      "approval_required": true
    },
    "tsa_service_continuity": {
      "issue_present": true,
      "draft_duration_months": 3,
      "target_duration_months": 12,
      "fallback_duration_months": 9,
      "required_service_codes": [
        "ERP",
        "FINANCE",
        "IT",
        "PAYROLL",
        "PROCUREMENT",
        "QUALITY_RECORDS",
        "REGULATORY"
      ],
      "approval_required": true
    },
    "restrictive_covenants": {
      "issue_present": true,
      "draft_non_compete_years": 5,
      "max_non_compete_years": 3,
      "affiliate_scope_allowed": false,
      "required_scope": "DIVESTED_LINE_EXISTING_GEOGRAPHIES",
      "non_solicit_scope": "DIVESTED_BUSINESS_CUSTOMERS_AND_EMPLOYEES_ONLY",
      "approval_required": true
    },
    "ip_transition": {
      "issue_present": true,
      "draft_trademark_phaseout_months": 18,
      "max_trademark_phaseout_months": 12,
      "broad_design_file_access": true,
      "required_scope": "NARROW_TRANSITIONAL_LICENSE_WITH_RETAINED_IP_BOUNDARIES",
      "approval_required": true
    },
    "escrow_and_deadline": {
      "issue_present": true,
      "general_escrow_percent": 12.5,
      "general_escrow_amount_usd": 39000000,
      "target_max_escrow_percent": 10.0,
      "signing_date": "2026-09-19",
      "draft_closing_deadline": "2026-10-31",
      "deadline_days_after_signing": 42,
      "minimum_deadline_days": 75,
      "deadline_escalation_required": true
    }
  }
}
